stoplight/__init__.py
stoplight/rc.py
stoplight/repo.py
stoplight/run.py
pystoplight-1.0.0.dist-info/entry_points.txt
pystoplight-1.0.0.dist-info/LICENSE
pystoplight-1.0.0.dist-info/WHEEL
pystoplight-1.0.0.dist-info/METADATA
pystoplight-1.0.0.dist-info/RECORD
