Metadata-Version: 2.1
Name: pystoplight
Version: 1.0.0
Summary: A tool that enables educators to easily control push access to GitHub Classroom assignment repositories.
Author: Maria Kim Heinert
Author-email: yeeunmariakim@gmail.com
Requires-Python: >=3.10,<4.0
Classifier: Programming Language :: Python :: 3
Classifier: Programming Language :: Python :: 3.10
Requires-Dist: requests (>=2.27.1,<3.0.0)
Requires-Dist: rich (>=11.1.0,<12.0.0)
Requires-Dist: toml (>=0.10.2,<0.11.0)
Requires-Dist: typer[all] (>=0.4.0,<0.5.0)
Requires-Dist: types-requests (>=2.27.8,<3.0.0)
Requires-Dist: types-toml (>=0.10.3,<0.11.0)
